cookiecutter/__init__.py
cookiecutter/__main__.py
cookiecutter/cli.py
cookiecutter/config.py
cookiecutter/environment.py
cookiecutter/exceptions.py
cookiecutter/extensions.py
cookiecutter/find.py
cookiecutter/generate.py
cookiecutter/hooks.py
cookiecutter/log.py
cookiecutter/main.py
cookiecutter/prompt.py
cookiecutter/replay.py
cookiecutter/repository.py
cookiecutter/utils.py
cookiecutter/vcs.py
cookiecutter/zipfile.py
awesome_cookiecutter-2.0.0.dist-info/AUTHORS.md
awesome_cookiecutter-2.0.0.dist-info/LICENSE
awesome_cookiecutter-2.0.0.dist-info/METADATA
awesome_cookiecutter-2.0.0.dist-info/WHEEL
awesome_cookiecutter-2.0.0.dist-info/entry_points.txt
awesome_cookiecutter-2.0.0.dist-info/top_level.txt
awesome_cookiecutter-2.0.0.dist-info/RECORD
