Metadata-Version: 2.1
Name: awesome-cookiecutter
Version: 2.0.0
Summary: A command-line utility that creates projects from project templates, e.g. creating a Python package project from a Python package project template.
Home-page: https://github.com/cookiecutter/cookiecutter
Author: Audrey Feldroy
Author-email: audreyr@gmail.com
License: BSD
Keywords: cookiecutter,Python,projects,project templates,Jinja2,skeleton,scaffolding,project directory,package,packaging
Platform: UNKNOWN
Classifier: Development Status :: 5 - Production/Stable
Classifier: Environment :: Console
Classifier: Intended Audience :: Developers
Classifier: Natural Language :: English
Classifier: License :: OSI Approved :: BSD License
Classifier: Programming Language :: Python :: 3 :: Only
Classifier: Programming Language :: Python :: 3
Classifier: Programming Language :: Python :: 3.6
Classifier: Programming Language :: Python :: 3.7
Classifier: Programming Language :: Python :: 3.8
Classifier: Programming Language :: Python :: 3.9
Classifier: Programming Language :: Python :: Implementation :: CPython
Classifier: Programming Language :: Python :: Implementation :: PyPy
Classifier: Programming Language :: Python
Classifier: Topic :: Software Development
Requires-Python: >=3.6
License-File: LICENSE
License-File: AUTHORS.md
Requires-Dist: binaryornot (>=0.4.4)
Requires-Dist: Jinja2 (<4.0.0,>=2.7)
Requires-Dist: click (<9.0.0,>=7.0)
Requires-Dist: pyyaml (>=5.3.1)
Requires-Dist: jinja2-time (>=0.2.0)
Requires-Dist: python-slugify (>=4.0.0)
Requires-Dist: requests (>=2.23.0)
